poold/__init__.py
poold/environment/__init__.py
poold/environment/environment.py
poold/environment/test.py
poold/hinters/__init__.py
poold/hinters/hinters.py
poold/learners/__init__.py
poold/learners/learners.py
poold/utils/__init__.py
poold/utils/general_utils.py
poold/utils/history.py
poold/utils/loss_utils.py
poold/utils/visualize.py
poold-0.0.5.dist-info/LICENSE
poold-0.0.5.dist-info/METADATA
poold-0.0.5.dist-info/WHEEL
poold-0.0.5.dist-info/top_level.txt
poold-0.0.5.dist-info/RECORD
