Metadata-Version: 2.1
Name: poold
Version: 0.0.5
Summary: Python library for Optimistic Online Learning under Delay.
Home-page: https://github.com/geflaspohler/poold
Author: Genevieve Flaspohler and Lester Mackey
Author-email: geflaspohler@gmail.com
License: UNKNOWN
Platform: UNKNOWN
Classifier: Programming Language :: Python :: 3
Classifier: License :: OSI Approved :: MIT License
Classifier: Operating System :: OS Independent
Requires-Python: >=3.6
License-File: LICENSE
Requires-Dist: numpy
Requires-Dist: pandas
Requires-Dist: matplotlib
Requires-Dist: seaborn
Requires-Dist: scipy
